odoo/addons/sm_carsharing_structure/__init__.py
odoo/addons/sm_carsharing_structure/__manifest__.py
odoo/addons/sm_carsharing_structure/models/__init__.py
odoo/addons/sm_carsharing_structure/models/models_cs_car.py
odoo/addons/sm_carsharing_structure/models/models_cs_car_service.py
odoo/addons/sm_carsharing_structure/models/models_cs_carconfig.py
odoo/addons/sm_carsharing_structure/models/models_cs_community.py
odoo/addons/sm_carsharing_structure/models/models_cs_helpdesk_ticket.py
odoo/addons/sm_carsharing_structure/models/models_cs_helpdesk_ticket_service_wizard.py
odoo/addons/sm_carsharing_structure/models/models_cs_production_unit.py
odoo/addons/sm_carsharing_structure/models/models_cs_task.py
odoo/addons/sm_carsharing_structure/models/models_cs_task_service_wizard.py
odoo/addons/sm_carsharing_structure/models/models_smp_car.py
odoo/addons/sm_carsharing_structure/models/models_smp_car_config.py
odoo/addons/sm_carsharing_structure/security/ir.model.access.csv
odoo/addons/sm_carsharing_structure/views/views.xml
odoo/addons/sm_carsharing_structure/views/views_cs_car.xml
odoo/addons/sm_carsharing_structure/views/views_cs_car_service.xml
odoo/addons/sm_carsharing_structure/views/views_cs_carconfig.xml
odoo/addons/sm_carsharing_structure/views/views_cs_community.xml
odoo/addons/sm_carsharing_structure/views/views_cs_helpdesk_ticket.xml
odoo/addons/sm_carsharing_structure/views/views_cs_helpdesk_ticket_wizard.xml
odoo/addons/sm_carsharing_structure/views/views_cs_production_unit.xml
odoo/addons/sm_carsharing_structure/views/views_cs_task.xml
odoo/addons/sm_carsharing_structure/views/views_cs_task_search.xml
odoo/addons/sm_carsharing_structure/views/views_cs_task_wizard.xml
odoo/addons/sm_carsharing_structure/views/views_db_car.xml
odoo/addons/sm_carsharing_structure/views/views_db_car_config.xml
odoo12_addon_sm_carsharing_structure-12.0.0.0.11.dist-info/METADATA
odoo12_addon_sm_carsharing_structure-12.0.0.0.11.dist-info/WHEEL
odoo12_addon_sm_carsharing_structure-12.0.0.0.11.dist-info/top_level.txt
odoo12_addon_sm_carsharing_structure-12.0.0.0.11.dist-info/RECORD
