Metadata-Version: 2.1
Name: odoo12-addon-sm-carsharing-structure
Version: 12.0.0.0.11
Summary: This module will organice everything that needs to be done in a car and a parking as projects. Also to define account structure for cs service
Home-page: https://www.sommobilitat.coop
Author: Som Mobilitat
License: UNKNOWN
Platform: UNKNOWN
Classifier: Programming Language :: Python
Classifier: Framework :: Odoo
Classifier: Framework :: Odoo :: 12.0
Requires-Python: >=3.5
Requires-Dist: odoo12-addon-helpdesk-mgmt
Requires-Dist: odoo12-addon-project-category
Requires-Dist: odoo12-addon-sm-partago-db
Requires-Dist: odoo12-addon-vertical-carsharing
Requires-Dist: odoo <12.1dev,>=12.0a
